test_package/__init__.py
test_package/test_module.py
test_rpa_util_class-0.0.3.dist-info/METADATA
test_rpa_util_class-0.0.3.dist-info/WHEEL
test_rpa_util_class-0.0.3.dist-info/top_level.txt
test_rpa_util_class-0.0.3.dist-info/RECORD
